molalign/__init__.py
molalign/molalign.py
molalignlib/__init__.py
molalignlib/alignment.f90
molalignlib/assignment.f90
molalignlib/assortment.f90
molalignlib/biasing.f90
molalignlib/chemdata.f90
molalignlib/chemutils.f90
molalignlib/discrete.f90
molalignlib/f2py_files
molalignlib/f90_files
molalignlib/hungarian.f90
molalignlib/linear.f90
molalignlib/maputils.f90
molalignlib/molalignlib.f90
molalignlib/molalignlib.py
molalignlib/printing.f90
molalignlib/random.f90
molalignlib/rnglib.f90
molalignlib/rotation.f90
molalignlib/settings.f90
molalignlib/sorting.f90
molalignlib/strutils.f90
molalignlib/translation.f90
molalignutil/__init__.py
molalignutil/compile.sh
molalignutil/gnu.env
molalignutil/link-pyext.sh
molalign-0.1.3.post1.dist-info/LICENSE
molalign-0.1.3.post1.dist-info/METADATA
molalign-0.1.3.post1.dist-info/WHEEL
molalign-0.1.3.post1.dist-info/entry_points.txt
molalign-0.1.3.post1.dist-info/top_level.txt
molalign-0.1.3.post1.dist-info/RECORD
