Metadata-Version: 2.1
Name: molalign
Version: 0.1.3.post1
Summary: Molecular alignment library
Home-page: https://github.com/qcuaeh/molalign
License: LGPLv3+
Keywords: molecules clusters rmsd
Platform: UNKNOWN
Classifier: Programming Language :: Python :: 3 :: Only
Classifier: License :: OSI Approved :: GNU Lesser General Public License v3 or later (LGPLv3+)
Classifier: Operating System :: POSIX
Requires-Python: >=3.3
Requires-Dist: numpy
Requires-Dist: ase
